__init__.py
app.py
cli.py
constants.py
core/__init__.py
core/chatgpt.py
core/coverletter.py
core/posting.py
core/resume.py
core/utils.py
gui/__init__.py
gui/applicant_info.py
gui/gui.py
gui/home.py
gui/job_info.py
gui/options.py
gui/screen.py
job_generator-1.0.3.dist-info/METADATA
job_generator-1.0.3.dist-info/WHEEL
job_generator-1.0.3.dist-info/top_level.txt
job_generator-1.0.3.dist-info/RECORD
