Metadata-Version: 2.1
Name: job-generator
Version: 1.0.3
Summary: A package to generate jobs for a given set of parameters
Author-email: Tim Hunter <thunte27@uwo.ca>
Project-URL: Homepage, https://github.com/tmhntr/job-generator
Project-URL: Bug Tracker, https://github.com/pypa/sampleproject/issues
Classifier: Programming Language :: Python :: 3
Classifier: License :: OSI Approved :: MIT License
Classifier: Operating System :: OS Independent
Requires-Python: >=3.7
Requires-Dist: beautifulsoup4 (==4.11.2)
Requires-Dist: numpy (==1.24.2)
Requires-Dist: openai (==0.27.1)
Requires-Dist: pdfkit (==1.0.0)
Requires-Dist: pyperclip (==1.8.2)
Requires-Dist: PySimpleGUI (==4.60.4)
Requires-Dist: python-dotenv (==1.0.0)
